atmlab/__init__.py
atmlab/common/__init__.py
atmlab/common/wsclient/__init__.py
atmlab/common/wsclient/abstract_ws.py
atmlab/common/wsclient/configuration.py
atmlab/common/wsclient/dataclasses_helpers.py
atmlab/common/wsclient/json_helpers.py
atmlab/common/wsclient/server_url_connection.py
atmlab/sinaps/__init__.py
atmlab/sinaps/center_hotspots.py
atmlab/sinaps/overloaded_period.py
atmlab/sinaps/sector_configuration_solution.py
atmlab/sinaps/sector_filter.py
atmlab/sinaps/wsclient/__init__.py
atmlab/sinaps/wsclient/cows.py
atmlab/sinaps/wsclient/runner.py
atmlab/sinapsis/__init__.py
atmlab/sinapsis/html_counts_generator.py
atmlab/sinapsis/nest_processor.py
atmlab/sinapsis/otmv.py
atmlab/sinapsis/resources/__init__.py
atmlab/sinapsis/resources/plot.js
atmlab/sinapsis/resources/styles.css
atmlab/sinapsis/traffic_counts.py
atmlab/sinapsis/traffic_counts_plot.py
atmlab/sinapsis/uces.py
atmlab/sinapsis/uceso.py
atmlab/sinapsis/wsclient/__init__.py
atmlab/sinapsis/wsclient/catalog_ws.py
atmlab/sinapsis/wsclient/scenario_factory.py
atmlab/sinapsis/wsclient/scenario_ws.py
atmlab/sinapsis/wsclient/uceso_ws.py
atmlab-1.0.1.dist-info/WHEEL
atmlab-1.0.1.dist-info/METADATA
atmlab-1.0.1.dist-info/RECORD
