Metadata-Version: 2.4
Name: atmlab
Version: 1.0.1
Summary: Python wrappers for the ONERA ATMLab libraries
Author: Judicaël Bedouet
Author-email: Judicaël Bedouet <Judicael.Bedouet@onera.fr>
License-Expression: LGPL-3.0-only
Requires-Dist: aniso8601>=10.0.1
Requires-Dist: certifi>=2025.10.5
Requires-Dist: dataclasses-json>=0.6.7
Requires-Dist: gamme
Requires-Dist: msgpack>=1.1.2
Requires-Dist: pyjwt>=2.10.1
Requires-Dist: pyyaml>=6.0.3
Requires-Dist: urllib3>=2.5.0
Requires-Dist: zstandard>=0.25.0
Requires-Dist: jpype1==1.5.0 ; extra == 'java'
Requires-Python: ==3.10.*
Provides-Extra: java
